zenith_trade_client/__init__.py
zenith_trade_client/client.py
zenith_trade_client/exceptions.py
zenith_trade_client/models.py
zenith_trade_client-0.1.3.dist-info/licenses/LICENSE
zenith_trade_client-0.1.3.dist-info/METADATA
zenith_trade_client-0.1.3.dist-info/WHEEL
zenith_trade_client-0.1.3.dist-info/top_level.txt
zenith_trade_client-0.1.3.dist-info/RECORD
