Metadata-Version: 2.4
Name: zenith-trade-client
Version: 0.1.3
Summary: Python client for accessing Zenith-Trade backend
Author-email: Shubham Pandey <shubhampandey@teesta.co>
License: MIT
Project-URL: Homepage, https://github.com/yourusername/zenith-trade-client
Project-URL: Issues, https://github.com/yourusername/zenith-trade-client/issues
Requires-Python: >=3.8
License-File: LICENSE
Requires-Dist: requests>=2.31.0
Requires-Dist: pydantic>=1.10
Dynamic: license-file
